graph2plan/__init__.py
graph2plan/constants.py
graph2plan/canonical/canonical_helpers.py
graph2plan/canonical/canonical_interfaces.py
graph2plan/canonical/canonical_order.py
graph2plan/canonical/check_canonical.py
graph2plan/dcel/examples.py
graph2plan/dcel/external.py
graph2plan/dcel/interfaces.py
graph2plan/dcel/original.py
graph2plan/dual/calculate_domains.py
graph2plan/dual/create_dual.py
graph2plan/dual/create_rectangular_floorplan.py
graph2plan/dual/examples.py
graph2plan/dual/helpers.py
graph2plan/dual/interfaces.py
graph2plan/export/export.py
graph2plan/export/interfaces.py
graph2plan/fourtp/draw_four_complete.py
graph2plan/fourtp/faces.py
graph2plan/fourtp/four_complete.py
graph2plan/fourtp/interfaces.py
graph2plan/fourtp/tests.py
graph2plan/helpers/auto_pos.py
graph2plan/helpers/geometry_interfaces.py
graph2plan/helpers/graph_checks.py
graph2plan/helpers/graph_interfaces.py
graph2plan/helpers/utils.py
graph2plan/main/examples.py
graph2plan/main/tests.py
graph2plan/rel/draw_rel.py
graph2plan/rel/rel2.py
graph2plan-0.1.1.dist-info/METADATA
graph2plan-0.1.1.dist-info/WHEEL
graph2plan-0.1.1.dist-info/entry_points.txt
graph2plan-0.1.1.dist-info/RECORD
