Metadata-Version: 2.4
Name: graph2plan
Version: 0.1.1
Summary: Add your description here
Author-email: Juliet Nwagwu Ume-Ezeoke <jnwagwu@stanford.edu>
Requires-Python: >=3.13
Requires-Dist: altair>=5.5.0
Requires-Dist: colored-traceback>=0.4.2
Requires-Dist: hypothesis-geometry>=8.0.0
Requires-Dist: hypothesis>=6.130.4
Requires-Dist: icecream>=2.1.4
Requires-Dist: ipykernel>=6.29.5
Requires-Dist: matplotlib>=3.10.1
Requires-Dist: networkx>=3.4.2
Requires-Dist: pyprojroot>=0.3.0
Requires-Dist: pytest>=8.3.5
Requires-Dist: rich>=14.0.0
Requires-Dist: shapely>=2.0.7
Requires-Dist: sympy>=1.13.3
Requires-Dist: types-networkx>=3.4.2.20250319
